extratools_text/__init__.py
extratools_text-0.1.3.dist-info/METADATA
extratools_text-0.1.3.dist-info/WHEEL
extratools_text-0.1.3.dist-info/licenses/LICENSE
extratools_text-0.1.3.dist-info/RECORD
