Metadata-Version: 2.4
Name: extratools-text
Version: 0.1.3
Project-URL: Repository, https://github.com/chuanconggao/extratools-text
Author-email: Chuancong Gao <chuanconggao@users.noreply.github.com>
License-Expression: MIT
License-File: LICENSE
Requires-Python: >=3.11
Requires-Dist: spacy>=3.8.7
Requires-Dist: toolz>=1.0.0
Provides-Extra: spacy-models
Requires-Dist: en-core-web-trf; extra == 'spacy-models'
